durin/__init__.py
durin/admin.py
durin/auth.py
durin/models.py
durin/permissions.py
durin/serializers.py
durin/settings.py
durin/signals.py
durin/throttling.py
durin/urls.py
durin/views.py
durin/management/__init__.py
durin/management/commands/__init__.py
durin/management/commands/create_client.py
durin/migrations/0001_initial.py
durin/migrations/0002_client_throttlerate.py
durin/migrations/__init__.py
example_project/migrations/0001_initial.py
example_project/migrations/__init__.py
django_rest_durin-1.1.0.dist-info/LICENSE
django_rest_durin-1.1.0.dist-info/METADATA
django_rest_durin-1.1.0.dist-info/WHEEL
django_rest_durin-1.1.0.dist-info/top_level.txt
django_rest_durin-1.1.0.dist-info/RECORD
