Metadata-Version: 2.1
Name: django-rest-durin
Version: 1.1.0
Summary: Per API client token authentication Module for django rest framework.
Home-page: https://github.com/eshaan7/django-rest-durin
Author: Eshaan Bansal
Author-email: eshaan7bansal@gmail.com
License: MIT
Project-URL: Documentation, https://django-rest-durin.readthedocs.io/
Project-URL: Funding, https://www.paypal.me/eshaanbansal
Project-URL: Source, https://github.com/eshaan7/django-rest-durin
Project-URL: Tracker, https://github.com/eshaan7/django-rest-durin/issues
Keywords: django rest authentication login token client auth
Classifier: Development Status :: 5 - Production/Stable
Classifier: Intended Audience :: Developers
Classifier: Topic :: Internet :: WWW/HTTP :: Session
Classifier: Environment :: Web Environment
Classifier: License :: OSI Approved :: MIT License
Classifier: Programming Language :: Python :: 3
Classifier: Programming Language :: Python :: 3.5
Classifier: Programming Language :: Python :: 3.6
Classifier: Programming Language :: Python :: 3.7
Classifier: Programming Language :: Python :: 3.8
Classifier: Programming Language :: Python :: 3.9
Classifier: Programming Language :: Python :: 3.10
Classifier: Topic :: Software Development :: Libraries :: Python Modules
Provides-Extra: dev
Provides-Extra: test
License-File: LICENSE
